[
  {
    "key": "com,twitter)/realdonaldtrump/status/508586831618015232",
    "timestamp": "2014-09-17 07:25:08+00:00",
    "url": "https://twitter.com/realDonaldTrump/status/508586831618015232",
    "mime_type": "text/html",
    "status_code": 200,
    "digest": "A2D243XJVGFUKLKHWDODKGSBCN6BGCSQ",
    "length": 23451,
    "raw_url": "http://web.archive.org/web/20140917072508id_/https://twitter.com/realDonaldTrump/status/508586831618015232",
    "view_url": "http://web.archive.org/web/20140917072508/https://twitter.com/realDonaldTrump/status/508586831618015232"
  },
  {
    "key": "com,twitter)/realdonaldtrump/status/508586831618015232",
    "timestamp": "2014-10-23 18:35:21+00:00",
    "url": "https://twitter.com/realDonaldTrump/status/508586831618015232",
    "mime_type": "text/html",
    "status_code": 200,
    "digest": "D5RD2OHIXMMTVWS2GTE2T3X3FZG3FZYB",
    "length": 25316,
    "raw_url": "http://web.archive.org/web/20141023183521id_/https://twitter.com/realDonaldTrump/status/508586831618015232",
    "view_url": "http://web.archive.org/web/20141023183521/https://twitter.com/realDonaldTrump/status/508586831618015232"
  },
  {
    "key": "com,twitter)/realdonaldtrump/status/508586831618015232?id=508586831618015232&lang=fi&screen_name=realdonaldtrump",
    "timestamp": "2015-08-22 12:09:25+00:00",
    "url": "https://twitter.com/realDonaldTrump/status/508586831618015232?screen_name=realDonaldTrump&id=508586831618015232&lang=fi",
    "mime_type": "text/html",
    "status_code": 200,
    "digest": "IDGVQDC4FUOOVPXLKR5OO2J7544LPHSI",
    "length": 26938,
    "raw_url": "http://web.archive.org/web/20150822120925id_/https://twitter.com/realDonaldTrump/status/508586831618015232?screen_name=realDonaldTrump&id=508586831618015232&lang=fi",
    "view_url": "http://web.archive.org/web/20150822120925/https://twitter.com/realDonaldTrump/status/508586831618015232?screen_name=realDonaldTrump&id=508586831618015232&lang=fi"
  },
  {
    "key": "com,twitter)/realdonaldtrump/status/508586831618015232?id=508586831618015232&lang=ko&screen_name=realdonaldtrump",
    "timestamp": "2015-08-24 00:19:28+00:00",
    "url": "https://twitter.com/realDonaldTrump/status/508586831618015232?screen_name=realDonaldTrump&id=508586831618015232&lang=ko",
    "mime_type": "text/html",
    "status_code": 200,
    "digest": "PC43WLVDGFXD5C4452UNC64655A3VOH2",
    "length": 28160,
    "raw_url": "http://web.archive.org/web/20150824001928id_/https://twitter.com/realDonaldTrump/status/508586831618015232?screen_name=realDonaldTrump&id=508586831618015232&lang=ko",
    "view_url": "http://web.archive.org/web/20150824001928/https://twitter.com/realDonaldTrump/status/508586831618015232?screen_name=realDonaldTrump&id=508586831618015232&lang=ko"
  },
  {
    "key": "com,twitter)/realdonaldtrump/status/508586831618015232?id=508586831618015232&lang=ms&screen_name=realdonaldtrump",
    "timestamp": "2015-09-10 22:25:07+00:00",
    "url": "https://twitter.com/realDonaldTrump/status/508586831618015232?screen_name=realDonaldTrump&id=508586831618015232&lang=ms",
    "mime_type": "text/html",
    "status_code": 200,
    "digest": "KB6BXCBIUPAOUIYGTRB7XHHC3N4SLDJS",
    "length": 25507,
    "raw_url": "http://web.archive.org/web/20150910222507id_/https://twitter.com/realDonaldTrump/status/508586831618015232?screen_name=realDonaldTrump&id=508586831618015232&lang=ms",
    "view_url": "http://web.archive.org/web/20150910222507/https://twitter.com/realDonaldTrump/status/508586831618015232?screen_name=realDonaldTrump&id=508586831618015232&lang=ms"
  },
  {
    "key": "com,twitter)/realdonaldtrump/status/508586831618015232?id=508586831618015232&lang=zh-tw&screen_name=realdonaldtrump",
    "timestamp": "2015-09-11 11:03:24+00:00",
    "url": "https://twitter.com/realDonaldTrump/status/508586831618015232?screen_name=realDonaldTrump&id=508586831618015232&lang=zh-tw",
    "mime_type": "text/html",
    "status_code": 200,
    "digest": "KVV2XKVYLFQW2EETUTCYX7UKMD45JB3L",
    "length": 28516,
    "raw_url": "http://web.archive.org/web/20150911110324id_/https://twitter.com/realDonaldTrump/status/508586831618015232?screen_name=realDonaldTrump&id=508586831618015232&lang=zh-tw",
    "view_url": "http://web.archive.org/web/20150911110324/https://twitter.com/realDonaldTrump/status/508586831618015232?screen_name=realDonaldTrump&id=508586831618015232&lang=zh-tw"
  },
  {
    "key": "com,twitter)/realdonaldtrump/status/508586831618015232?id=508586831618015232&lang=hu&screen_name=realdonaldtrump",
    "timestamp": "2015-09-14 08:00:44+00:00",
    "url": "https://twitter.com/realDonaldTrump/status/508586831618015232?screen_name=realDonaldTrump&id=508586831618015232&lang=hu",
    "mime_type": "text/html",
    "status_code": 200,
    "digest": "F6WOH6P66OCWNNGWSN6XOASL75WV3BO2",
    "length": 28369,
    "raw_url": "http://web.archive.org/web/20150914080044id_/https://twitter.com/realDonaldTrump/status/508586831618015232?screen_name=realDonaldTrump&id=508586831618015232&lang=hu",
    "view_url": "http://web.archive.org/web/20150914080044/https://twitter.com/realDonaldTrump/status/508586831618015232?screen_name=realDonaldTrump&id=508586831618015232&lang=hu"
  },
  {
    "key": "com,twitter)/realdonaldtrump/status/508586831618015232?id=508586831618015232&screen_name=realdonaldtrump",
    "timestamp": "2015-09-15 06:46:20+00:00",
    "url": "https://twitter.com/realDonaldTrump/status/508586831618015232?screen_name=realDonaldTrump&id=508586831618015232",
    "mime_type": "text/html",
    "status_code": 200,
    "digest": "S3WPTJQHSG67VOYUZYDIGF6GB6BVGPLU",
    "length": 25559,
    "raw_url": "http://web.archive.org/web/20150915064620id_/https://twitter.com/realDonaldTrump/status/508586831618015232?screen_name=realDonaldTrump&id=508586831618015232",
    "view_url": "http://web.archive.org/web/20150915064620/https://twitter.com/realDonaldTrump/status/508586831618015232?screen_name=realDonaldTrump&id=508586831618015232"
  },
  {
    "key": "com,twitter)/realdonaldtrump/status/508586831618015232?id=508586831618015232&lang=es&screen_name=realdonaldtrump",
    "timestamp": "2015-09-19 00:21:30+00:00",
    "url": "https://twitter.com/realDonaldTrump/status/508586831618015232?screen_name=realDonaldTrump&id=508586831618015232&lang=es",
    "mime_type": "text/html",
    "status_code": 200,
    "digest": "Y5OICJTJD5AYGK2NGNGJZ3YUKHXHOALB",
    "length": 26505,
    "raw_url": "http://web.archive.org/web/20150919002130id_/https://twitter.com/realDonaldTrump/status/508586831618015232?screen_name=realDonaldTrump&id=508586831618015232&lang=es",
    "view_url": "http://web.archive.org/web/20150919002130/https://twitter.com/realDonaldTrump/status/508586831618015232?screen_name=realDonaldTrump&id=508586831618015232&lang=es"
  },
  {
    "key": "com,twitter)/realdonaldtrump/status/508586831618015232?id=508586831618015232&lang=nl&screen_name=realdonaldtrump",
    "timestamp": "2015-09-20 09:07:18+00:00",
    "url": "https://twitter.com/realDonaldTrump/status/508586831618015232?screen_name=realDonaldTrump&id=508586831618015232&lang=nl",
    "mime_type": "text/html",
    "status_code": 200,
    "digest": "WBBFUW4EBONYY2PJPX7BBMON6LUTUTGC",
    "length": 25838,
    "raw_url": "http://web.archive.org/web/20150920090718id_/https://twitter.com/realDonaldTrump/status/508586831618015232?screen_name=realDonaldTrump&id=508586831618015232&lang=nl",
    "view_url": "http://web.archive.org/web/20150920090718/https://twitter.com/realDonaldTrump/status/508586831618015232?screen_name=realDonaldTrump&id=508586831618015232&lang=nl"
  },
  {
    "key": "com,twitter)/realdonaldtrump/status/508586831618015232?id=508586831618015232&lang=fr&screen_name=realdonaldtrump",
    "timestamp": "2015-09-25 02:23:27+00:00",
    "url": "https://twitter.com/realDonaldTrump/status/508586831618015232?screen_name=realDonaldTrump&id=508586831618015232&lang=fr",
    "mime_type": "text/html",
    "status_code": 200,
    "digest": "SU73XMGNLPNUYZPGUP6ERUPW7ROVGPTC",
    "length": 26128,
    "raw_url": "http://web.archive.org/web/20150925022327id_/https://twitter.com/realDonaldTrump/status/508586831618015232?screen_name=realDonaldTrump&id=508586831618015232&lang=fr",
    "view_url": "http://web.archive.org/web/20150925022327/https://twitter.com/realDonaldTrump/status/508586831618015232?screen_name=realDonaldTrump&id=508586831618015232&lang=fr"
  },
  {
    "key": "com,twitter)/realdonaldtrump/status/508586831618015232?id=508586831618015232&lang=ar&screen_name=realdonaldtrump",
    "timestamp": "2015-09-27 09:25:29+00:00",
    "url": "https://twitter.com/realDonaldTrump/status/508586831618015232?screen_name=realDonaldTrump&id=508586831618015232&lang=ar",
    "mime_type": "text/html",
    "status_code": 200,
    "digest": "3NDO2ADCB7HOGTTA5NPCW2SBCXPDJ7AK",
    "length": 26987,
    "raw_url": "http://web.archive.org/web/20150927092529id_/https://twitter.com/realDonaldTrump/status/508586831618015232?screen_name=realDonaldTrump&id=508586831618015232&lang=ar",
    "view_url": "http://web.archive.org/web/20150927092529/https://twitter.com/realDonaldTrump/status/508586831618015232?screen_name=realDonaldTrump&id=508586831618015232&lang=ar"
  },
  {
    "key": "com,twitter)/realdonaldtrump/status/508586831618015232?id=508586831618015232&lang=de&screen_name=realdonaldtrump",
    "timestamp": "2015-10-03 06:32:59+00:00",
    "url": "https://twitter.com/realDonaldTrump/status/508586831618015232?screen_name=realDonaldTrump&id=508586831618015232&lang=de",
    "mime_type": "text/html",
    "status_code": 200,
    "digest": "VSWFZXDKYP7OQ2CFPQH7CXNQ473IXB34",
    "length": 26167,
    "raw_url": "http://web.archive.org/web/20151003063259id_/https://twitter.com/realDonaldTrump/status/508586831618015232?screen_name=realDonaldTrump&id=508586831618015232&lang=de",
    "view_url": "http://web.archive.org/web/20151003063259/https://twitter.com/realDonaldTrump/status/508586831618015232?screen_name=realDonaldTrump&id=508586831618015232&lang=de"
  },
  {
    "key": "com,twitter)/realdonaldtrump/status/508586831618015232?id=508586831618015232&lang=vi&screen_name=realdonaldtrump",
    "timestamp": "2015-10-13 04:03:29+00:00",
    "url": "https://twitter.com/realDonaldTrump/status/508586831618015232?screen_name=realDonaldTrump&id=508586831618015232&lang=vi",
    "mime_type": "text/html",
    "status_code": 200,
    "digest": "UTHLABS44IBAL7TO6E4S7LAW7A3NYRG6",
    "length": 26446,
    "raw_url": "http://web.archive.org/web/20151013040329id_/https://twitter.com/realDonaldTrump/status/508586831618015232?screen_name=realDonaldTrump&id=508586831618015232&lang=vi",
    "view_url": "http://web.archive.org/web/20151013040329/https://twitter.com/realDonaldTrump/status/508586831618015232?screen_name=realDonaldTrump&id=508586831618015232&lang=vi"
  },
  {
    "key": "com,twitter)/realdonaldtrump/status/508586831618015232?id=508586831618015232&lang=en-gb&screen_name=realdonaldtrump",
    "timestamp": "2015-10-20 07:42:04+00:00",
    "url": "https://twitter.com/realDonaldTrump/status/508586831618015232?screen_name=realDonaldTrump&id=508586831618015232&lang=en-gb",
    "mime_type": "text/html",
    "status_code": 200,
    "digest": "ZT2GQKCFAYWVXO44KXF7GMHTG24OAAOY",
    "length": 26466,
    "raw_url": "http://web.archive.org/web/20151020074204id_/https://twitter.com/realDonaldTrump/status/508586831618015232?screen_name=realDonaldTrump&id=508586831618015232&lang=en-gb",
    "view_url": "http://web.archive.org/web/20151020074204/https://twitter.com/realDonaldTrump/status/508586831618015232?screen_name=realDonaldTrump&id=508586831618015232&lang=en-gb"
  },
  {
    "key": "com,twitter)/realdonaldtrump/status/508586831618015232?id=508586831618015232&lang=sv&screen_name=realdonaldtrump",
    "timestamp": "2015-10-20 21:24:21+00:00",
    "url": "https://twitter.com/realDonaldTrump/status/508586831618015232?screen_name=realDonaldTrump&id=508586831618015232&lang=sv",
    "mime_type": "text/html",
    "status_code": 200,
    "digest": "2NQXZNIOT3GKULHYY5H2NRJI22TDS6L7",
    "length": 25841,
    "raw_url": "http://web.archive.org/web/20151020212421id_/https://twitter.com/realDonaldTrump/status/508586831618015232?screen_name=realDonaldTrump&id=508586831618015232&lang=sv",
    "view_url": "http://web.archive.org/web/20151020212421/https://twitter.com/realDonaldTrump/status/508586831618015232?screen_name=realDonaldTrump&id=508586831618015232&lang=sv"
  },
  {
    "key": "com,twitter)/realdonaldtrump/status/508586831618015232?id=508586831618015232&lang=gl&screen_name=realdonaldtrump",
    "timestamp": "2015-10-28 14:45:53+00:00",
    "url": "https://twitter.com/realDonaldTrump/status/508586831618015232?screen_name=realDonaldTrump&id=508586831618015232&lang=gl",
    "mime_type": "text/html",
    "status_code": 200,
    "digest": "RQ3AUBZ4LQRPB62WLL274ABRRKFXISNM",
    "length": 25605,
    "raw_url": "http://web.archive.org/web/20151028144553id_/https://twitter.com/realDonaldTrump/status/508586831618015232?screen_name=realDonaldTrump&id=508586831618015232&lang=gl",
    "view_url": "http://web.archive.org/web/20151028144553/https://twitter.com/realDonaldTrump/status/508586831618015232?screen_name=realDonaldTrump&id=508586831618015232&lang=gl"
  },
  {
    "key": "com,twitter)/realdonaldtrump/status/508586831618015232?id=508586831618015232&lang=id&screen_name=realdonaldtrump",
    "timestamp": "2015-10-28 22:09:29+00:00",
    "url": "https://twitter.com/realDonaldTrump/status/508586831618015232?screen_name=realDonaldTrump&id=508586831618015232&lang=id",
    "mime_type": "text/html",
    "status_code": 200,
    "digest": "UJGXC7RH3DWXTAGS7MWNCVT5KMTVA2BO",
    "length": 27121,
    "raw_url": "http://web.archive.org/web/20151028220929id_/https://twitter.com/realDonaldTrump/status/508586831618015232?screen_name=realDonaldTrump&id=508586831618015232&lang=id",
    "view_url": "http://web.archive.org/web/20151028220929/https://twitter.com/realDonaldTrump/status/508586831618015232?screen_name=realDonaldTrump&id=508586831618015232&lang=id"
  },
  {
    "key": "com,twitter)/realdonaldtrump/status/508586831618015232?id=508586831618015232&lang=pl&screen_name=realdonaldtrump",
    "timestamp": "2015-10-30 10:08:37+00:00",
    "url": "https://twitter.com/realDonaldTrump/status/508586831618015232?screen_name=realDonaldTrump&id=508586831618015232&lang=pl",
    "mime_type": "text/html",
    "status_code": 200,
    "digest": "S3ODQGNUEIO4H7I74V7BBVXBS4KHK6HJ",
    "length": 26238,
    "raw_url": "http://web.archive.org/web/20151030100837id_/https://twitter.com/realDonaldTrump/status/508586831618015232?screen_name=realDonaldTrump&id=508586831618015232&lang=pl",
    "view_url": "http://web.archive.org/web/20151030100837/https://twitter.com/realDonaldTrump/status/508586831618015232?screen_name=realDonaldTrump&id=508586831618015232&lang=pl"
  },
  {
    "key": "com,twitter)/realdonaldtrump/status/508586831618015232?id=508586831618015232&lang=zh-cn&screen_name=realdonaldtrump",
    "timestamp": "2015-11-13 11:35:20+00:00",
    "url": "https://twitter.com/realDonaldTrump/status/508586831618015232?screen_name=realDonaldTrump&id=508586831618015232&lang=zh-cn",
    "mime_type": "text/html",
    "status_code": 200,
    "digest": "CUBCZP4IIU6KV7XO647ROUPMX2EL6IFZ",
    "length": 26541,
    "raw_url": "http://web.archive.org/web/20151113113520id_/https://twitter.com/realDonaldTrump/status/508586831618015232?screen_name=realDonaldTrump&id=508586831618015232&lang=zh-cn",
    "view_url": "http://web.archive.org/web/20151113113520/https://twitter.com/realDonaldTrump/status/508586831618015232?screen_name=realDonaldTrump&id=508586831618015232&lang=zh-cn"
  },
  {
    "key": "com,twitter)/realdonaldtrump/status/508586831618015232?id=508586831618015232&lang=th&screen_name=realdonaldtrump",
    "timestamp": "2015-11-21 09:56:16+00:00",
    "url": "https://twitter.com/realDonaldTrump/status/508586831618015232?screen_name=realDonaldTrump&id=508586831618015232&lang=th",
    "mime_type": "text/html",
    "status_code": 200,
    "digest": "CNO4KSB4AMMQBDKBJ2XZCUFLDE7FSDPU",
    "length": 27347,
    "raw_url": "http://web.archive.org/web/20151121095616id_/https://twitter.com/realDonaldTrump/status/508586831618015232?screen_name=realDonaldTrump&id=508586831618015232&lang=th",
    "view_url": "http://web.archive.org/web/20151121095616/https://twitter.com/realDonaldTrump/status/508586831618015232?screen_name=realDonaldTrump&id=508586831618015232&lang=th"
  },
  {
    "key": "com,twitter)/realdonaldtrump/status/508586831618015232?id=508586831618015232&lang=cs&screen_name=realdonaldtrump",
    "timestamp": "2015-11-25 17:08:42+00:00",
    "url": "https://twitter.com/realDonaldTrump/status/508586831618015232?screen_name=realDonaldTrump&id=508586831618015232&lang=cs",
    "mime_type": "text/html",
    "status_code": 200,
    "digest": "6LVSUU22GJWQX5L7HF2N37HXHRQHJD6Y",
    "length": 26578,
    "raw_url": "http://web.archive.org/web/20151125170842id_/https://twitter.com/realDonaldTrump/status/508586831618015232?screen_name=realDonaldTrump&id=508586831618015232&lang=cs",
    "view_url": "http://web.archive.org/web/20151125170842/https://twitter.com/realDonaldTrump/status/508586831618015232?screen_name=realDonaldTrump&id=508586831618015232&lang=cs"
  },
  {
    "key": "com,twitter)/realdonaldtrump/status/508586831618015232?id=508586831618015232&lang=fa&screen_name=realdonaldtrump",
    "timestamp": "2015-11-30 08:03:24+00:00",
    "url": "https://twitter.com/realDonaldTrump/status/508586831618015232?screen_name=realDonaldTrump&id=508586831618015232&lang=fa",
    "mime_type": "text/html",
    "status_code": 200,
    "digest": "ZP7VAGHHDQ56V46KJHIOE5XFO7CI4ECG",
    "length": 28484,
    "raw_url": "http://web.archive.org/web/20151130080324id_/https://twitter.com/realDonaldTrump/status/508586831618015232?screen_name=realDonaldTrump&id=508586831618015232&lang=fa",
    "view_url": "http://web.archive.org/web/20151130080324/https://twitter.com/realDonaldTrump/status/508586831618015232?screen_name=realDonaldTrump&id=508586831618015232&lang=fa"
  },
  {
    "key": "com,twitter)/realdonaldtrump/status/508586831618015232?id=508586831618015232&lang=ro&screen_name=realdonaldtrump",
    "timestamp": "2015-12-02 02:38:30+00:00",
    "url": "https://twitter.com/realDonaldTrump/status/508586831618015232?screen_name=realDonaldTrump&id=508586831618015232&lang=ro",
    "mime_type": "text/html",
    "status_code": 200,
    "digest": "JO25LGTRVSGISO5YOUNUEAM7LHBAV64K",
    "length": 25006,
    "raw_url": "http://web.archive.org/web/20151202023830id_/https://twitter.com/realDonaldTrump/status/508586831618015232?screen_name=realDonaldTrump&id=508586831618015232&lang=ro",
    "view_url": "http://web.archive.org/web/20151202023830/https://twitter.com/realDonaldTrump/status/508586831618015232?screen_name=realDonaldTrump&id=508586831618015232&lang=ro"
  },
  {
    "key": "com,twitter)/realdonaldtrump/status/508586831618015232?id=508586831618015232&lang=hi&screen_name=realdonaldtrump",
    "timestamp": "2015-12-02 11:40:17+00:00",
    "url": "https://twitter.com/realDonaldTrump/status/508586831618015232?screen_name=realDonaldTrump&id=508586831618015232&lang=hi",
    "mime_type": "text/html",
    "status_code": 200,
    "digest": "2KV24UEDX34HJEUSDF2UFU3LNX34GI5V",
    "length": 28810,
    "raw_url": "http://web.archive.org/web/20151202114017id_/https://twitter.com/realDonaldTrump/status/508586831618015232?screen_name=realDonaldTrump&id=508586831618015232&lang=hi",
    "view_url": "http://web.archive.org/web/20151202114017/https://twitter.com/realDonaldTrump/status/508586831618015232?screen_name=realDonaldTrump&id=508586831618015232&lang=hi"
  },
  {
    "key": "com,twitter)/realdonaldtrump/status/508586831618015232?id=508586831618015232&lang=no&screen_name=realdonaldtrump",
    "timestamp": "2015-12-02 15:43:38+00:00",
    "url": "https://twitter.com/realDonaldTrump/status/508586831618015232?screen_name=realDonaldTrump&id=508586831618015232&lang=no",
    "mime_type": "text/html",
    "status_code": 200,
    "digest": "GNLMFV6XAJY2SDJSJN3ZFJQ66WW5WYHL",
    "length": 27426,
    "raw_url": "http://web.archive.org/web/20151202154338id_/https://twitter.com/realDonaldTrump/status/508586831618015232?screen_name=realDonaldTrump&id=508586831618015232&lang=no",
    "view_url": "http://web.archive.org/web/20151202154338/https://twitter.com/realDonaldTrump/status/508586831618015232?screen_name=realDonaldTrump&id=508586831618015232&lang=no"
  },
  {
    "key": "com,twitter)/realdonaldtrump/status/508586831618015232?id=508586831618015232&lang=eu&screen_name=realdonaldtrump",
    "timestamp": "2015-12-12 02:50:57+00:00",
    "url": "https://twitter.com/realDonaldTrump/status/508586831618015232?screen_name=realDonaldTrump&id=508586831618015232&lang=eu",
    "mime_type": "text/html",
    "status_code": 200,
    "digest": "5OTR344RSICC4AA3RQHAUN54TO7NO2VB",
    "length": 24595,
    "raw_url": "http://web.archive.org/web/20151212025057id_/https://twitter.com/realDonaldTrump/status/508586831618015232?screen_name=realDonaldTrump&id=508586831618015232&lang=eu",
    "view_url": "http://web.archive.org/web/20151212025057/https://twitter.com/realDonaldTrump/status/508586831618015232?screen_name=realDonaldTrump&id=508586831618015232&lang=eu"
  },
  {
    "key": "com,twitter)/realdonaldtrump/status/508586831618015232?id=508586831618015232&lang=ru&screen_name=realdonaldtrump",
    "timestamp": "2015-12-14 06:49:19+00:00",
    "url": "https://twitter.com/realDonaldTrump/status/508586831618015232?screen_name=realDonaldTrump&id=508586831618015232&lang=ru",
    "mime_type": "text/html",
    "status_code": 200,
    "digest": "K7A7523LDJSULA72QOPIS7S4GVFLY7X5",
    "length": 26004,
    "raw_url": "http://web.archive.org/web/20151214064919id_/https://twitter.com/realDonaldTrump/status/508586831618015232?screen_name=realDonaldTrump&id=508586831618015232&lang=ru",
    "view_url": "http://web.archive.org/web/20151214064919/https://twitter.com/realDonaldTrump/status/508586831618015232?screen_name=realDonaldTrump&id=508586831618015232&lang=ru"
  },
  {
    "key": "com,twitter)/realdonaldtrump/status/508586831618015232?id=508586831618015232&lang=en&screen_name=realdonaldtrump",
    "timestamp": "2015-12-17 04:46:42+00:00",
    "url": "https://twitter.com/realDonaldTrump/status/508586831618015232?screen_name=realDonaldTrump&id=508586831618015232&lang=en",
    "mime_type": "text/html",
    "status_code": 200,
    "digest": "AIKIWSSKLQPJHPODJ52YHEVROQ5SFZRL",
    "length": 25024,
    "raw_url": "http://web.archive.org/web/20151217044642id_/https://twitter.com/realDonaldTrump/status/508586831618015232?screen_name=realDonaldTrump&id=508586831618015232&lang=en",
    "view_url": "http://web.archive.org/web/20151217044642/https://twitter.com/realDonaldTrump/status/508586831618015232?screen_name=realDonaldTrump&id=508586831618015232&lang=en"
  },
  {
    "key": "com,twitter)/realdonaldtrump/status/508586831618015232?id=508586831618015232&lang=tr&screen_name=realdonaldtrump",
    "timestamp": "2015-12-19 16:17:04+00:00",
    "url": "https://twitter.com/realDonaldTrump/status/508586831618015232?screen_name=realDonaldTrump&id=508586831618015232&lang=tr",
    "mime_type": "text/html",
    "status_code": 200,
    "digest": "NIN23GQWX2WRBHDJQPNEADXZK5MTSRYO",
    "length": 26053,
    "raw_url": "http://web.archive.org/web/20151219161704id_/https://twitter.com/realDonaldTrump/status/508586831618015232?screen_name=realDonaldTrump&id=508586831618015232&lang=tr",
    "view_url": "http://web.archive.org/web/20151219161704/https://twitter.com/realDonaldTrump/status/508586831618015232?screen_name=realDonaldTrump&id=508586831618015232&lang=tr"
  },
  {
    "key": "com,twitter)/realdonaldtrump/status/508586831618015232?id=508586831618015232&lang=it&screen_name=realdonaldtrump",
    "timestamp": "2015-12-21 15:03:16+00:00",
    "url": "https://twitter.com/realDonaldTrump/status/508586831618015232?screen_name=realDonaldTrump&id=508586831618015232&lang=it",
    "mime_type": "text/html",
    "status_code": 200,
    "digest": "2CLAWXVTWWHZJHZNHWEGNVLCANA4UXRI",
    "length": 25585,
    "raw_url": "http://web.archive.org/web/20151221150316id_/https://twitter.com/realDonaldTrump/status/508586831618015232?screen_name=realDonaldTrump&id=508586831618015232&lang=it",
    "view_url": "http://web.archive.org/web/20151221150316/https://twitter.com/realDonaldTrump/status/508586831618015232?screen_name=realDonaldTrump&id=508586831618015232&lang=it"
  },
  {
    "key": "com,twitter)/realdonaldtrump/status/508586831618015232?id=508586831618015232&lang=bn&screen_name=realdonaldtrump",
    "timestamp": "2015-12-24 14:21:06+00:00",
    "url": "https://twitter.com/realDonaldTrump/status/508586831618015232?screen_name=realDonaldTrump&id=508586831618015232&lang=bn",
    "mime_type": "text/html",
    "status_code": 200,
    "digest": "PFQQURVVPQZWQSRRAJ2NRO3QKUMNZ3VJ",
    "length": 25145,
    "raw_url": "http://web.archive.org/web/20151224142106id_/https://twitter.com/realDonaldTrump/status/508586831618015232?screen_name=realDonaldTrump&id=508586831618015232&lang=bn",
    "view_url": "http://web.archive.org/web/20151224142106/https://twitter.com/realDonaldTrump/status/508586831618015232?screen_name=realDonaldTrump&id=508586831618015232&lang=bn"
  },
  {
    "key": "com,twitter)/realdonaldtrump/status/508586831618015232?id=508586831618015232&lang=uk&screen_name=realdonaldtrump",
    "timestamp": "2015-12-24 19:36:03+00:00",
    "url": "https://twitter.com/realDonaldTrump/status/508586831618015232?screen_name=realDonaldTrump&id=508586831618015232&lang=uk",
    "mime_type": "text/html",
    "status_code": 200,
    "digest": "JXV75AYHYECVTJD2UKJIGZAGR7KU3HYC",
    "length": 26850,
    "raw_url": "http://web.archive.org/web/20151224193603id_/https://twitter.com/realDonaldTrump/status/508586831618015232?screen_name=realDonaldTrump&id=508586831618015232&lang=uk",
    "view_url": "http://web.archive.org/web/20151224193603/https://twitter.com/realDonaldTrump/status/508586831618015232?screen_name=realDonaldTrump&id=508586831618015232&lang=uk"
  },
  {
    "key": "com,twitter)/realdonaldtrump/status/508586831618015232?id=508586831618015232&lang=ja&screen_name=realdonaldtrump",
    "timestamp": "2015-12-30 02:47:14+00:00",
    "url": "https://twitter.com/realDonaldTrump/status/508586831618015232?screen_name=realDonaldTrump&id=508586831618015232&lang=ja",
    "mime_type": "text/html",
    "status_code": 200,
    "digest": "IV6NYFQICAC4Z7W626RSJMOJ6CA4N2GP",
    "length": 24954,
    "raw_url": "http://web.archive.org/web/20151230024714id_/https://twitter.com/realDonaldTrump/status/508586831618015232?screen_name=realDonaldTrump&id=508586831618015232&lang=ja",
    "view_url": "http://web.archive.org/web/20151230024714/https://twitter.com/realDonaldTrump/status/508586831618015232?screen_name=realDonaldTrump&id=508586831618015232&lang=ja"
  },
  {
    "key": "com,twitter)/realdonaldtrump/status/508586831618015232?id=508586831618015232&lang=ur&screen_name=realdonaldtrump",
    "timestamp": "2016-01-02 10:44:07+00:00",
    "url": "https://twitter.com/realDonaldTrump/status/508586831618015232?screen_name=realDonaldTrump&id=508586831618015232&lang=ur",
    "mime_type": "text/html",
    "status_code": 200,
    "digest": "CHBDYGIXPLMTE7DZCT6Y3EZKIBM2VZBU",
    "length": 24947,
    "raw_url": "http://web.archive.org/web/20160102104407id_/https://twitter.com/realDonaldTrump/status/508586831618015232?screen_name=realDonaldTrump&id=508586831618015232&lang=ur",
    "view_url": "http://web.archive.org/web/20160102104407/https://twitter.com/realDonaldTrump/status/508586831618015232?screen_name=realDonaldTrump&id=508586831618015232&lang=ur"
  },
  {
    "key": "com,twitter)/realdonaldtrump/status/508586831618015232?id=508586831618015232&lang=da&screen_name=realdonaldtrump",
    "timestamp": "2016-01-05 06:41:36+00:00",
    "url": "https://twitter.com/realDonaldTrump/status/508586831618015232?screen_name=realDonaldTrump&id=508586831618015232&lang=da",
    "mime_type": "text/html",
    "status_code": 200,
    "digest": "H6OPPLZOSNEOHDSPM25TPLUJY73YFUHG",
    "length": 24005,
    "raw_url": "http://web.archive.org/web/20160105064136id_/https://twitter.com/realDonaldTrump/status/508586831618015232?screen_name=realDonaldTrump&id=508586831618015232&lang=da",
    "view_url": "http://web.archive.org/web/20160105064136/https://twitter.com/realDonaldTrump/status/508586831618015232?screen_name=realDonaldTrump&id=508586831618015232&lang=da"
  },
  {
    "key": "com,twitter)/realdonaldtrump/status/508586831618015232?id=508586831618015232&lang=pt&screen_name=realdonaldtrump",
    "timestamp": "2016-01-22 21:59:24+00:00",
    "url": "https://twitter.com/realDonaldTrump/status/508586831618015232?screen_name=realDonaldTrump&id=508586831618015232&lang=pt",
    "mime_type": "text/html",
    "status_code": 200,
    "digest": "KZY5CEJ5FRNM4GZMZJYW7LO4C2E2DK34",
    "length": 27613,
    "raw_url": "http://web.archive.org/web/20160122215924id_/https://twitter.com/realDonaldTrump/status/508586831618015232?screen_name=realDonaldTrump&id=508586831618015232&lang=pt",
    "view_url": "http://web.archive.org/web/20160122215924/https://twitter.com/realDonaldTrump/status/508586831618015232?screen_name=realDonaldTrump&id=508586831618015232&lang=pt"
  },
  {
    "key": "com,twitter)/realdonaldtrump/status/508586831618015232?id=508586831618015232&lang=fil&screen_name=realdonaldtrump",
    "timestamp": "2016-01-23 12:49:13+00:00",
    "url": "https://twitter.com/realDonaldTrump/status/508586831618015232?screen_name=realDonaldTrump&id=508586831618015232&lang=fil",
    "mime_type": "text/html",
    "status_code": 200,
    "digest": "K6AIE5GG7TFB47J745FK5MH7KSIGCHZL",
    "length": 27110,
    "raw_url": "http://web.archive.org/web/20160123124913id_/https://twitter.com/realDonaldTrump/status/508586831618015232?screen_name=realDonaldTrump&id=508586831618015232&lang=fil",
    "view_url": "http://web.archive.org/web/20160123124913/https://twitter.com/realDonaldTrump/status/508586831618015232?screen_name=realDonaldTrump&id=508586831618015232&lang=fil"
  },
  {
    "key": "com,twitter)/realdonaldtrump/status/508586831618015232?id=508586831618015232&lang=el&screen_name=realdonaldtrump",
    "timestamp": "2016-01-26 00:25:02+00:00",
    "url": "https://twitter.com/realDonaldTrump/status/508586831618015232?screen_name=realDonaldTrump&id=508586831618015232&lang=el",
    "mime_type": "text/html",
    "status_code": 200,
    "digest": "SNDPT5N3M3SB5O5PEHL4AIE76SSWEK6I",
    "length": 29169,
    "raw_url": "http://web.archive.org/web/20160126002502id_/https://twitter.com/realDonaldTrump/status/508586831618015232?screen_name=realDonaldTrump&id=508586831618015232&lang=el",
    "view_url": "http://web.archive.org/web/20160126002502/https://twitter.com/realDonaldTrump/status/508586831618015232?screen_name=realDonaldTrump&id=508586831618015232&lang=el"
  },
  {
    "key": "com,twitter)/realdonaldtrump/status/508586831618015232?id=508586831618015232&lang=he&screen_name=realdonaldtrump",
    "timestamp": "2016-01-29 19:10:35+00:00",
    "url": "https://twitter.com/realDonaldTrump/status/508586831618015232?screen_name=realDonaldTrump&id=508586831618015232&lang=he",
    "mime_type": "text/html",
    "status_code": 200,
    "digest": "NZ65UVFTHSP6ZVTOSTBYPCZ43RLUKS36",
    "length": 27852,
    "raw_url": "http://web.archive.org/web/20160129191035id_/https://twitter.com/realDonaldTrump/status/508586831618015232?screen_name=realDonaldTrump&id=508586831618015232&lang=he",
    "view_url": "http://web.archive.org/web/20160129191035/https://twitter.com/realDonaldTrump/status/508586831618015232?screen_name=realDonaldTrump&id=508586831618015232&lang=he"
  },
  {
    "key": "com,twitter)/realdonaldtrump/status/508586831618015232?lang=en-gb",
    "timestamp": "2016-02-10 22:00:54+00:00",
    "url": "https://twitter.com/realdonaldtrump/status/508586831618015232?lang=en-gb",
    "mime_type": "text/html",
    "status_code": 200,
    "digest": "XFUYN43JIELYOP3GRVAIOTFTUV64N3AZ",
    "length": 26544,
    "raw_url": "http://web.archive.org/web/20160210220054id_/https://twitter.com/realdonaldtrump/status/508586831618015232?lang=en-gb",
    "view_url": "http://web.archive.org/web/20160210220054/https://twitter.com/realdonaldtrump/status/508586831618015232?lang=en-gb"
  },
  {
    "key": "com,twitter)/realdonaldtrump/status/508586831618015232",
    "timestamp": "2016-03-30 07:17:35+00:00",
    "url": "https://twitter.com/realDonaldTrump/status/508586831618015232",
    "mime_type": "text/html",
    "status_code": 200,
    "digest": "RQKW2VAZZ2QQJ2T2UO7PZN5N3JMZT727",
    "length": 29184,
    "raw_url": "http://web.archive.org/web/20160330071735id_/https://twitter.com/realDonaldTrump/status/508586831618015232",
    "view_url": "http://web.archive.org/web/20160330071735/https://twitter.com/realDonaldTrump/status/508586831618015232"
  },
  {
    "key": "com,twitter)/realdonaldtrump/status/508586831618015232",
    "timestamp": "2017-07-15 16:40:19+00:00",
    "url": "https://twitter.com/realDonaldTrump/status/508586831618015232",
    "mime_type": "text/html",
    "status_code": 200,
    "digest": "GLQFM2RYU3IAXDIC4QBZ23OOE5DB6ETR",
    "length": 39183,
    "raw_url": "http://web.archive.org/web/20170715164019id_/https://twitter.com/realDonaldTrump/status/508586831618015232",
    "view_url": "http://web.archive.org/web/20170715164019/https://twitter.com/realDonaldTrump/status/508586831618015232"
  },
  {
    "key": "com,twitter)/realdonaldtrump/status/508586831618015232",
    "timestamp": "2017-12-13 14:35:27+00:00",
    "url": "https://twitter.com/realDonaldTrump/status/508586831618015232",
    "mime_type": "text/html",
    "status_code": 200,
    "digest": "MSEDAXW6WAXPVOLKOFH3WUXOFXFVYM3L",
    "length": 49522,
    "raw_url": "http://web.archive.org/web/20171213143527id_/https://twitter.com/realDonaldTrump/status/508586831618015232",
    "view_url": "http://web.archive.org/web/20171213143527/https://twitter.com/realDonaldTrump/status/508586831618015232"
  },
  {
    "key": "com,twitter)/realdonaldtrump/status/508586831618015232",
    "timestamp": "2018-03-03 13:19:20+00:00",
    "url": "https://twitter.com/realDonaldTrump/status/508586831618015232",
    "mime_type": "text/html",
    "status_code": 200,
    "digest": "65GWJYPWFY5RRJCWKZCGHJTLOXW3H6UE",
    "length": 42497,
    "raw_url": "http://web.archive.org/web/20180303131920id_/https://twitter.com/realDonaldTrump/status/508586831618015232",
    "view_url": "http://web.archive.org/web/20180303131920/https://twitter.com/realDonaldTrump/status/508586831618015232"
  },
  {
    "key": "com,twitter)/realdonaldtrump/status/508586831618015232",
    "timestamp": "2018-03-16 18:11:12+00:00",
    "url": "https://twitter.com/realDonaldTrump/status/508586831618015232",
    "mime_type": "text/html",
    "status_code": 200,
    "digest": "ORH6ZQAKDBHJX2TDZGA4GSTO4YAUBO66",
    "length": 48345,
    "raw_url": "http://web.archive.org/web/20180316181112id_/https://twitter.com/realDonaldTrump/status/508586831618015232",
    "view_url": "http://web.archive.org/web/20180316181112/https://twitter.com/realDonaldTrump/status/508586831618015232"
  },
  {
    "key": "com,twitter)/realdonaldtrump/status/508586831618015232",
    "timestamp": "2018-04-11 17:08:17+00:00",
    "url": "https://twitter.com/realDonaldTrump/status/508586831618015232",
    "mime_type": "text/html",
    "status_code": 200,
    "digest": "U4DIAY2SLDZGFFCXQ3U7FPGR33KNKPOE",
    "length": 44567,
    "raw_url": "http://web.archive.org/web/20180411170817id_/https://twitter.com/realDonaldTrump/status/508586831618015232",
    "view_url": "http://web.archive.org/web/20180411170817/https://twitter.com/realDonaldTrump/status/508586831618015232"
  },
  {
    "key": "com,twitter)/realdonaldtrump/status/508586831618015232",
    "timestamp": "2020-07-10 19:38:46+00:00",
    "url": "https://twitter.com/realDonaldTrump/status/508586831618015232",
    "mime_type": "text/html",
    "status_code": 200,
    "digest": "D6AZZWEXBOMVOTQQVFACHZUAU2C6HOSS",
    "length": 65253,
    "raw_url": "http://web.archive.org/web/20200710193846id_/https://twitter.com/realDonaldTrump/status/508586831618015232",
    "view_url": "http://web.archive.org/web/20200710193846/https://twitter.com/realDonaldTrump/status/508586831618015232"
  },
  {
    "key": "com,twitter)/realdonaldtrump/status/508586831618015232",
    "timestamp": "2020-11-06 10:10:17+00:00",
    "url": "https://twitter.com/realDonaldTrump/status/508586831618015232",
    "mime_type": "text/html",
    "status_code": 200,
    "digest": "PKQI6YWSEVNKII3QNRIWPDT3D7X3IE7N",
    "length": 85575,
    "raw_url": "http://web.archive.org/web/20201106101017id_/https://twitter.com/realDonaldTrump/status/508586831618015232",
    "view_url": "http://web.archive.org/web/20201106101017/https://twitter.com/realDonaldTrump/status/508586831618015232"
  }
]